steammarket/__init__.py
steammarket/steammarket.py
steammarket-2.0.0.dist-info/METADATA
steammarket-2.0.0.dist-info/WHEEL
steammarket-2.0.0.dist-info/licenses/LICENSE
steammarket-2.0.0.dist-info/RECORD
