Metadata-Version: 2.3
Name: steammarket
Version: 2.0.0
Summary: A Python API for getting prices from the Steam market.
Project-URL: Homepage, https://github.com/matyifkbt/PySteamMarket
Project-URL: Issues, https://github.com/matyifkbt/pysteammarket/issues
Project-URL: Changelog, https://github.com/matyifkbt/pysteammarket/blob/master/CHANGELOG.md
Author-email: Matyi <mmatyi@caesar.elte.hu>
Requires-Python: >=3.10
Requires-Dist: requests>=2.32.3
